microprobe/definitions/riscv/__init__.py
microprobe/definitions/riscv/doc/__init__.py
microprobe/definitions/riscv/doc/examples.rst
microprobe/definitions/riscv/doc/examples_riscv.rst
microprobe/definitions/riscv/env/__init__.py
microprobe/definitions/riscv/env/riscv_bp3.py
microprobe/definitions/riscv/env/riscv_eprocessor_sim.py
microprobe/definitions/riscv/env/riscv_linux_gcc.py
microprobe/definitions/riscv/env/riscv_linux_gcc_nolibc.py
microprobe/definitions/riscv/env/riscv_riscy_sim.py
microprobe/definitions/riscv/env/riscv_sargantana_sim.py
microprobe/definitions/riscv/env/riscv_spike_sim.py
microprobe/definitions/riscv/env/riscv_test_p.py
microprobe/definitions/riscv/examples/Makefile.in
microprobe/definitions/riscv/examples/Makefrag
microprobe/definitions/riscv/examples/README.md
microprobe/definitions/riscv/examples/__init__.py
microprobe/definitions/riscv/examples/configure.ac
microprobe/definitions/riscv/examples/riscv_branch.py
microprobe/definitions/riscv/examples/riscv_ipc.py
microprobe/definitions/riscv/examples/riscv_ipc_c.py
microprobe/definitions/riscv/examples/riscv_ipc_seq.py
microprobe/definitions/riscv/examples/riscv_ipc/Makefile
microprobe/definitions/riscv/examples/riscv_ipc/__init__.py
microprobe/definitions/riscv/isa/__init__.py
microprobe/definitions/riscv/isa/riscv-boom/__init__.py
microprobe/definitions/riscv/isa/riscv-boom/getcontext.S
microprobe/definitions/riscv/isa/riscv-boom/instruction.yaml
microprobe/definitions/riscv/isa/riscv-boom/isa.py
microprobe/definitions/riscv/isa/riscv-boom/isa.yaml
microprobe/definitions/riscv/isa/riscv-boom/setcontext.S
microprobe/definitions/riscv/isa/riscv-common/__init__.py
microprobe/definitions/riscv/isa/riscv-common/comparator.py
microprobe/definitions/riscv/isa/riscv-common/generator.py
microprobe/definitions/riscv/isa/riscv-common/getcontext.S
microprobe/definitions/riscv/isa/riscv-common/instruction.py
microprobe/definitions/riscv/isa/riscv-common/instruction.yaml
microprobe_target_riscv-0.5.20250911152917.dist-info/licenses/LICENSE
microprobe_target_riscv-0.5.20250911152917.dist-info/METADATA
microprobe_target_riscv-0.5.20250911152917.dist-info/WHEEL
microprobe_target_riscv-0.5.20250911152917.dist-info/top_level.txt
microprobe_target_riscv-0.5.20250911152917.dist-info/RECORD
